{
  "type" : "FeatureCollection",
  "features" : [{"type":"Feature","id":1,"geometry":{"type":"Point","coordinates":[16.373057112000026,48.200412448000066]},"properties":{"ObjectID":1,"Loc_name":"World","Status":"M","Score":97.879999999999995,"Match_type":"A","Match_addr":"Canovagasse 4, 1010, Innere Stadt, Wien","LongLabel":"Canovagasse 4, 1010, Innere Stadt, Wien, AUT","ShortLabel":"Canovagasse 4","Addr_type":"PointAddress","Type":"","PlaceName":"","Place_addr":"Canovagasse 4, 1010, Innere Stadt, Wien","Phone":"","URL":"","Rank":20,"AddBldg":"","AddNum":"4","AddNumFrom":"","AddNumTo":"","AddRange":"","Side":"","StPreDir":"","StPreType":"","StName":"Canovagasse","StType":"","StDir":"","BldgType":"","BldgName":"","LevelType":"","LevelName":"","UnitType":"","UnitName":"","SubAddr":"","StAddr":"Canovagasse 4","Block":"","Sector":"","Nbrhd":"","District":"Innere Stadt","City":"Wien","MetroArea":"","Subregion":"Wien","Region":"Wien","RegionAbbr":"","Territory":"","Zone":"","Postal":"1010","PostalExt":"","Country":"AUT","CntryName":"Österreich","LangCode":"GER","Distance":0,"X":16.373132130304999,"Y":48.200373974721998,"DisplayX":16.373057112270999,"DisplayY":48.200412447658003,"Xmin":16.372057112271001,"Xmax":16.374057112271,"Ymin":48.199412447657998,"Ymax":48.201412447658001,"ExInfo":"1010 | WIEN WIEN STADT WIEN","StrucType":"","StrucDet":"","IN_Address":"Canovagasse 4, 1010, Innere Stadt, Wien, Wien(Stadt), Wien","IN_Address2":null,"IN_Address3":null,"IN_Neighborhood":null,"IN_City":"Wien","IN_Subregion":null,"IN_Region":null,"IN_Postal":"1010","IN_PostalExt":null,"IN_CountryCode":null,"USER_ObjectID":13,"USER_FacilityID":255,"USER_FacilityRank":1,"USER_Address":"Canovagasse 4, 1010, Innere Stadt, Wien, Wien(Stadt), Wien","USER_City":"Wien","USER_Postal":1010,"USER_Cluster":"Location 7","USER_IncidentCurbApproach":2,"USER_FacilityCurbApproach":1,"USER_IncidentID":7,"USER_StartTime":null,"USER_EndTime":null,"USER_StartTimeUTC":null,"USER_EndTimeUTC":null,"USER_Total_Minutes":null,"USER_Total_TimeAt1KPH":null,"USER_Total_TravelTime":0.085238281713279185,"USER_Total_TruckMinutes":null,"USER_Total_TruckTravelTime":null,"USER_Total_WalkTime":null,"USER_Total_Kilometers":0.02841665700013463,"USER_Total_Miles":null,"USER_Shape_Length":0.00027133438835357491}},{"type":"Feature","id":2,"geometry":{"type":"Point","coordinates":[16.37288411000003,48.20073842000005]},"properties":{"ObjectID":2,"Loc_name":"World","Status":"M","Score":98.170000000000002,"Match_type":"A","Match_addr":"Bösendorferstraße 12, 1010, Innere Stadt, Wien","LongLabel":"Bösendorferstraße 12, 1010, Innere Stadt, Wien, AUT","ShortLabel":"Bösendorferstraße 12","Addr_type":"PointAddress","Type":"","PlaceName":"","Place_addr":"Bösendorferstraße 12, 1010, Innere Stadt, Wien","Phone":"","URL":"","Rank":20,"AddBldg":"","AddNum":"12","AddNumFrom":"","AddNumTo":"","AddRange":"","Side":"","StPreDir":"","StPreType":"","StName":"Bösendorferstraße","StType":"","StDir":"","BldgType":"","BldgName":"","LevelType":"","LevelName":"","UnitType":"","UnitName":"","SubAddr":"","StAddr":"Bösendorferstraße 12","Block":"","Sector":"","Nbrhd":"","District":"Innere Stadt","City":"Wien","MetroArea":"","Subregion":"Wien","Region":"Wien","RegionAbbr":"","Territory":"","Zone":"","Postal":"1010","PostalExt":"","Country":"AUT","CntryName":"Österreich","LangCode":"GER","Distance":0,"X":16.372894670988,"Y":48.20079483008,"DisplayX":16.37288410979,"DisplayY":48.200738419872003,"Xmin":16.371884109789999,"Xmax":16.373884109790001,"Ymin":48.199738419871998,"Ymax":48.201738419872001,"ExInfo":"1010 | WIEN WIEN STADT WIEN","StrucType":"","StrucDet":"","IN_Address":"Bösendorferstraße 12, 1010, Innere Stadt, Wien, Wien(Stadt), Wien","IN_Address2":null,"IN_Address3":null,"IN_Neighborhood":null,"IN_City":"Wien","IN_Subregion":null,"IN_Region":null,"IN_Postal":"1010","IN_PostalExt":null,"IN_CountryCode":null,"USER_ObjectID":14,"USER_FacilityID":257,"USER_FacilityRank":2,"USER_Address":"Bösendorferstraße 12, 1010, Innere Stadt, Wien, Wien(Stadt), Wien","USER_City":"Wien","USER_Postal":1010,"USER_Cluster":"Location 7","USER_IncidentCurbApproach":2,"USER_FacilityCurbApproach":1,"USER_IncidentID":7,"USER_StartTime":null,"USER_EndTime":null,"USER_StartTimeUTC":null,"USER_EndTimeUTC":null,"USER_Total_Minutes":null,"USER_Total_TimeAt1KPH":null,"USER_Total_TravelTime":0.47837017939414173,"USER_Total_TruckMinutes":null,"USER_Total_TruckTravelTime":null,"USER_Total_WalkTime":null,"USER_Total_Kilometers":0.1073804698929203,"USER_Total_Miles":null,"USER_Shape_Length":0.0011513616147510129}}]
}