{
  "type" : "FeatureCollection",
  "features" : [{"type":"Feature","id":1,"geometry":{"type":"Point","coordinates":[16.352600826000071,48.200429924000048]},"properties":{"ObjectID":1,"Loc_name":"World","Status":"M","Score":97.769999999999996,"Match_type":"A","Match_addr":"Kirchengasse 10, 1070, Neubau, Wien, Wien(Stadt), Wien","LongLabel":"Kirchengasse 10, 1070, Neubau, Wien, Wien(Stadt), Wien, AUT","ShortLabel":"Kirchengasse 10","Addr_type":"PointAddress","Type":"","PlaceName":"","Place_addr":"Kirchengasse 10, 1070, Neubau, Wien, Wien(Stadt), Wien","Phone":"","URL":"","Rank":20,"AddBldg":"","AddNum":"10","AddNumFrom":"","AddNumTo":"","AddRange":"","Side":"","StPreDir":"","StPreType":"","StName":"Kirchengasse","StType":"","StDir":"","BldgType":"","BldgName":"","LevelType":"","LevelName":"","UnitType":"","UnitName":"","SubAddr":"","StAddr":"Kirchengasse 10","Block":"","Sector":"","Nbrhd":"","District":"Neubau","City":"Wien","MetroArea":"","Subregion":"Wien(Stadt)","Region":"Wien","RegionAbbr":"","Territory":"","Zone":"","Postal":"1070","PostalExt":"","Country":"AUT","CntryName":"Österreich","LangCode":"GER","Distance":0,"X":16.352535866364999,"Y":48.200403185654999,"DisplayX":16.352600826115001,"DisplayY":48.200429923926002,"Xmin":16.351600826115,"Xmax":16.353600826114999,"Ymin":48.199429923925997,"Ymax":48.201429923926,"ExInfo":"1070 | WIEN | WIEN","StrucType":"","StrucDet":"","IN_Address":"Kirchengasse 10, 1070, Neubau, Wien, Wien(Stadt), Wien","IN_Address2":null,"IN_Address3":null,"IN_Neighborhood":null,"IN_City":"Wien","IN_Subregion":null,"IN_Region":null,"IN_Postal":"1070","IN_PostalExt":null,"IN_CountryCode":null,"USER_ObjectID":20,"USER_FacilityID":293,"USER_FacilityRank":2,"USER_Address":"Kirchengasse 10, 1070, Neubau, Wien, Wien(Stadt), Wien","USER_City":"Wien","USER_Postal":1070,"USER_Cluster":"Location 10","USER_IncidentCurbApproach":1,"USER_FacilityCurbApproach":1,"USER_IncidentID":10,"USER_StartTime":null,"USER_EndTime":null,"USER_StartTimeUTC":null,"USER_EndTimeUTC":null,"USER_Total_Minutes":null,"USER_Total_TimeAt1KPH":null,"USER_Total_TravelTime":1.3540318113814001,"USER_Total_TruckMinutes":null,"USER_Total_TruckTravelTime":null,"USER_Total_WalkTime":null,"USER_Total_Kilometers":0.32811887629689879,"USER_Total_Miles":null,"USER_Shape_Length":0.0039765051813583779}},{"type":"Feature","id":2,"geometry":{"type":"Point","coordinates":[16.356442839000067,48.200599406000038]},"properties":{"ObjectID":2,"Loc_name":"World","Status":"M","Score":97.939999999999998,"Match_type":"A","Match_addr":"Mariahilfer Straße 22-24, 1070, Neubau, Wien, Wien(Stadt), Wien","LongLabel":"Mariahilfer Straße 22-24, 1070, Neubau, Wien, Wien(Stadt), Wien, AUT","ShortLabel":"Mariahilfer Straße 22-24","Addr_type":"PointAddress","Type":"","PlaceName":"","Place_addr":"Mariahilfer Straße 22-24, 1070, Neubau, Wien, Wien(Stadt), Wien","Phone":"","URL":"","Rank":20,"AddBldg":"","AddNum":"22-24","AddNumFrom":"22","AddNumTo":"24","AddRange":"22-24","Side":"","StPreDir":"","StPreType":"","StName":"Mariahilfer Straße","StType":"","StDir":"","BldgType":"","BldgName":"","LevelType":"","LevelName":"","UnitType":"","UnitName":"","SubAddr":"","StAddr":"Mariahilfer Straße 22-24","Block":"","Sector":"","Nbrhd":"","District":"Neubau","City":"Wien","MetroArea":"","Subregion":"Wien(Stadt)","Region":"Wien","RegionAbbr":"","Territory":"","Zone":"","Postal":"1070","PostalExt":"","Country":"AUT","CntryName":"Österreich","LangCode":"GER","Distance":0,"X":16.356471840457999,"Y":48.200483903382001,"DisplayX":16.356442839073001,"DisplayY":48.200599406008003,"Xmin":16.355442839073,"Xmax":16.357442839072998,"Ymin":48.199599406007998,"Ymax":48.201599406008,"ExInfo":"1070 | WIEN | WIEN","StrucType":"","StrucDet":"","IN_Address":"Mariahilfer Straße 22-24, 1070, Neubau, Wien, Wien(Stadt), Wien","IN_Address2":null,"IN_Address3":null,"IN_Neighborhood":null,"IN_City":"Wien","IN_Subregion":null,"IN_Region":null,"IN_Postal":"1070","IN_PostalExt":null,"IN_CountryCode":null,"USER_ObjectID":19,"USER_FacilityID":133,"USER_FacilityRank":1,"USER_Address":"Mariahilfer Straße 22-24, 1070, Neubau, Wien, Wien(Stadt), Wien","USER_City":"Wien","USER_Postal":1070,"USER_Cluster":"Location 10","USER_IncidentCurbApproach":1,"USER_FacilityCurbApproach":1,"USER_IncidentID":10,"USER_StartTime":null,"USER_EndTime":null,"USER_StartTimeUTC":null,"USER_EndTimeUTC":null,"USER_Total_Minutes":null,"USER_Total_TimeAt1KPH":null,"USER_Total_TravelTime":0.90125961431850643,"USER_Total_TruckMinutes":null,"USER_Total_TruckTravelTime":null,"USER_Total_WalkTime":null,"USER_Total_Kilometers":0.25575563270564178,"USER_Total_Miles":null,"USER_Shape_Length":0.0027340153099481559}}]
}