{
  "type" : "FeatureCollection",
  "features" : [{"type":"Feature","id":1,"geometry":{"type":"Point","coordinates":[16.398541954000052,48.195200413000066]},"properties":{"ObjectID":1,"Loc_name":"World","Status":"M","Score":97.840000000000003,"Match_type":"A","Match_addr":"Rabengasse 16, 1030, Landstraße, Wien, Wien(Stadt), Wien","LongLabel":"Rabengasse 16, 1030, Landstraße, Wien, Wien(Stadt), Wien, AUT","ShortLabel":"Rabengasse 16","Addr_type":"PointAddress","Type":"","PlaceName":"","Place_addr":"Rabengasse 16, 1030, Landstraße, Wien, Wien(Stadt), Wien","Phone":"","URL":"","Rank":20,"AddBldg":"","AddNum":"16","AddNumFrom":"","AddNumTo":"","AddRange":"","Side":"","StPreDir":"","StPreType":"","StName":"Rabengasse","StType":"","StDir":"","BldgType":"","BldgName":"","LevelType":"","LevelName":"","UnitType":"","UnitName":"","SubAddr":"","StAddr":"Rabengasse 16","Block":"","Sector":"","Nbrhd":"","District":"Landstraße","City":"Wien","MetroArea":"","Subregion":"Wien(Stadt)","Region":"Wien","RegionAbbr":"","Territory":"","Zone":"","Postal":"1030","PostalExt":"","Country":"AUT","CntryName":"Österreich","LangCode":"GER","Distance":0,"X":16.398603979684001,"Y":48.195143834779003,"DisplayX":16.398541953599999,"DisplayY":48.195200412624999,"Xmin":16.397541953600001,"Xmax":16.3995419536,"Ymin":48.194200412625001,"Ymax":48.196200412624997,"ExInfo":"1030 | WIEN | WIEN","StrucType":"","StrucDet":"","IN_Address":"Rabengasse 16, 1030, Landstraße, Wien, Wien(Stadt), Wien","IN_Address2":null,"IN_Address3":null,"IN_Neighborhood":null,"IN_City":"Wien","IN_Subregion":null,"IN_Region":null,"IN_Postal":"1030","IN_PostalExt":null,"IN_CountryCode":null,"USER_ObjectID":44,"USER_FacilityID":343,"USER_FacilityRank":2,"USER_Address":"Rabengasse 16, 1030, Landstraße, Wien, Wien(Stadt), Wien","USER_City":"Wien","USER_Postal":1030,"USER_Cluster":"Location 22","USER_IncidentCurbApproach":1,"USER_FacilityCurbApproach":1,"USER_IncidentID":22,"USER_StartTime":null,"USER_EndTime":null,"USER_StartTimeUTC":null,"USER_EndTimeUTC":null,"USER_Total_Minutes":null,"USER_Total_TimeAt1KPH":null,"USER_Total_TravelTime":2.9772177778077702,"USER_Total_TruckMinutes":null,"USER_Total_TruckTravelTime":null,"USER_Total_WalkTime":null,"USER_Total_Kilometers":0.57892744205611313,"USER_Total_Miles":null,"USER_Shape_Length":0.0061559198270056213}},{"type":"Feature","id":2,"geometry":{"type":"Point","coordinates":[16.40029058600004,48.190926983000054]},"properties":{"ObjectID":2,"Loc_name":"World","Status":"M","Score":98.109999999999999,"Match_type":"A","Match_addr":"Landstraßer Hauptstraße 148A, 1030, Landstraße, Wien, Wien(Stadt), Wien","LongLabel":"Landstraßer Hauptstraße 148A, 1030, Landstraße, Wien, Wien(Stadt), Wien, AUT","ShortLabel":"Landstraßer Hauptstraße 148A","Addr_type":"PointAddress","Type":"","PlaceName":"","Place_addr":"Landstraßer Hauptstraße 148A, 1030, Landstraße, Wien, Wien(Stadt), Wien","Phone":"","URL":"","Rank":20,"AddBldg":"","AddNum":"148A","AddNumFrom":"","AddNumTo":"","AddRange":"","Side":"","StPreDir":"","StPreType":"","StName":"Landstraßer Hauptstraße","StType":"","StDir":"","BldgType":"","BldgName":"","LevelType":"","LevelName":"","UnitType":"","UnitName":"","SubAddr":"","StAddr":"Landstraßer Hauptstraße 148A","Block":"","Sector":"","Nbrhd":"","District":"Landstraße","City":"Wien","MetroArea":"","Subregion":"Wien(Stadt)","Region":"Wien","RegionAbbr":"","Territory":"","Zone":"","Postal":"1030","PostalExt":"","Country":"AUT","CntryName":"Österreich","LangCode":"GER","Distance":0,"X":16.400427127442999,"Y":48.191067715263998,"DisplayX":16.400290586240999,"DisplayY":48.190926983110003,"Xmin":16.399290586241001,"Xmax":16.401290586241,"Ymin":48.189926983109999,"Ymax":48.191926983110001,"ExInfo":"1030 | WIEN | WIEN","StrucType":"","StrucDet":"","IN_Address":"Landstraßer Hauptstraße 148A, 1030, Landstraße, Wien, Wien(Stadt), Wien","IN_Address2":null,"IN_Address3":null,"IN_Neighborhood":null,"IN_City":"Wien","IN_Subregion":null,"IN_Region":null,"IN_Postal":"1030","IN_PostalExt":null,"IN_CountryCode":null,"USER_ObjectID":43,"USER_FacilityID":13,"USER_FacilityRank":1,"USER_Address":"Landstraßer Hauptstraße 148A, 1030, Landstraße, Wien, Wien(Stadt), Wien","USER_City":"Wien","USER_Postal":1030,"USER_Cluster":"Location 22","USER_IncidentCurbApproach":1,"USER_FacilityCurbApproach":2,"USER_IncidentID":22,"USER_StartTime":null,"USER_EndTime":null,"USER_StartTimeUTC":null,"USER_EndTimeUTC":null,"USER_Total_Minutes":null,"USER_Total_TimeAt1KPH":null,"USER_Total_TravelTime":2.0198360427503999,"USER_Total_TruckMinutes":null,"USER_Total_TruckTravelTime":null,"USER_Total_WalkTime":null,"USER_Total_Kilometers":0.24300770074728709,"USER_Total_Miles":null,"USER_Shape_Length":0.0026944129176893531}}]
}