{
  "type" : "FeatureCollection",
  "features" : [{"type":"Feature","id":1,"geometry":{"type":"Point","coordinates":[16.381660633000024,48.185457037000049]},"properties":{"ObjectID":1,"Loc_name":"World","Status":"M","Score":97.879999999999995,"Match_type":"A","Match_addr":"Canettistraße 3A, 1100, Favoriten, Wien, Wien(Stadt), Wien","LongLabel":"Canettistraße 3A, 1100, Favoriten, Wien, Wien(Stadt), Wien, AUT","ShortLabel":"Canettistraße 3A","Addr_type":"PointAddress","Type":"","PlaceName":"","Place_addr":"Canettistraße 3A, 1100, Favoriten, Wien, Wien(Stadt), Wien","Phone":"","URL":"","Rank":20,"AddBldg":"","AddNum":"3A","AddNumFrom":"","AddNumTo":"","AddRange":"","Side":"","StPreDir":"","StPreType":"","StName":"Canettistraße","StType":"","StDir":"","BldgType":"","BldgName":"","LevelType":"","LevelName":"","UnitType":"","UnitName":"","SubAddr":"","StAddr":"Canettistraße 3A","Block":"","Sector":"","Nbrhd":"","District":"Favoriten","City":"Wien","MetroArea":"","Subregion":"Wien(Stadt)","Region":"Wien","RegionAbbr":"","Territory":"","Zone":"","Postal":"1100","PostalExt":"","Country":"AUT","CntryName":"Österreich","LangCode":"GER","Distance":0,"X":16.381569102583999,"Y":48.185612353582997,"DisplayX":16.381660632967002,"DisplayY":48.185457036917001,"Xmin":16.380660632967,"Xmax":16.382660632966999,"Ymin":48.184457036917003,"Ymax":48.186457036916998,"ExInfo":"1100 | WIEN | WIEN","StrucType":"","StrucDet":"","IN_Address":"Canettistraße 3A, 1100, Favoriten, Wien, Wien(Stadt), Wien","IN_Address2":null,"IN_Address3":null,"IN_Neighborhood":null,"IN_City":"Wien","IN_Subregion":null,"IN_Region":null,"IN_Postal":"1100","IN_PostalExt":null,"IN_CountryCode":null,"USER_ObjectID":7,"USER_FacilityID":323,"USER_FacilityRank":1,"USER_Address":"Canettistraße 3A, 1100, Favoriten, Wien, Wien(Stadt), Wien","USER_City":"Wien","USER_Postal":1100,"USER_Cluster":"Location 4","USER_IncidentCurbApproach":1,"USER_FacilityCurbApproach":1,"USER_IncidentID":4,"USER_StartTime":null,"USER_EndTime":null,"USER_StartTimeUTC":null,"USER_EndTimeUTC":null,"USER_Total_Minutes":null,"USER_Total_TimeAt1KPH":null,"USER_Total_TravelTime":2.31215911542815,"USER_Total_TruckMinutes":null,"USER_Total_TruckTravelTime":null,"USER_Total_WalkTime":null,"USER_Total_Kilometers":0.33845656530774382,"USER_Total_Miles":null,"USER_Shape_Length":0.0040293453210285199}},{"type":"Feature","id":2,"geometry":{"type":"Point","coordinates":[16.379291656000078,48.185502341000074]},"properties":{"ObjectID":2,"Loc_name":"World","Status":"M","Score":97.859999999999999,"Match_type":"A","Match_addr":"Canettistraße 6, 1100, Favoriten, Wien, Wien(Stadt), Wien","LongLabel":"Canettistraße 6, 1100, Favoriten, Wien, Wien(Stadt), Wien, AUT","ShortLabel":"Canettistraße 6","Addr_type":"PointAddress","Type":"","PlaceName":"","Place_addr":"Canettistraße 6, 1100, Favoriten, Wien, Wien(Stadt), Wien","Phone":"","URL":"","Rank":20,"AddBldg":"","AddNum":"6","AddNumFrom":"","AddNumTo":"","AddRange":"","Side":"","StPreDir":"","StPreType":"","StName":"Canettistraße","StType":"","StDir":"","BldgType":"","BldgName":"","LevelType":"","LevelName":"","UnitType":"","UnitName":"","SubAddr":"","StAddr":"Canettistraße 6","Block":"","Sector":"","Nbrhd":"","District":"Favoriten","City":"Wien","MetroArea":"","Subregion":"Wien(Stadt)","Region":"Wien","RegionAbbr":"","Territory":"","Zone":"","Postal":"1100","PostalExt":"","Country":"AUT","CntryName":"Österreich","LangCode":"GER","Distance":0,"X":16.379279837188999,"Y":48.185423551214001,"DisplayX":16.379291655671999,"DisplayY":48.185502341103998,"Xmin":16.378291655672001,"Xmax":16.380291655672,"Ymin":48.184502341104,"Ymax":48.186502341103001,"ExInfo":"1100 | WIEN | WIEN","StrucType":"","StrucDet":"","IN_Address":"Canettistraße 6, 1100, Favoriten, Wien, Wien(Stadt), Wien","IN_Address2":null,"IN_Address3":null,"IN_Neighborhood":null,"IN_City":"Wien","IN_Subregion":null,"IN_Region":null,"IN_Postal":"1100","IN_PostalExt":null,"IN_CountryCode":null,"USER_ObjectID":8,"USER_FacilityID":382,"USER_FacilityRank":2,"USER_Address":"Canettistraße 6, 1100, Favoriten, Wien, Wien(Stadt), Wien","USER_City":"Wien","USER_Postal":1100,"USER_Cluster":"Location 4","USER_IncidentCurbApproach":1,"USER_FacilityCurbApproach":2,"USER_IncidentID":4,"USER_StartTime":null,"USER_EndTime":null,"USER_StartTimeUTC":null,"USER_EndTimeUTC":null,"USER_Total_Minutes":null,"USER_Total_TimeAt1KPH":null,"USER_Total_TravelTime":2.862310634947149,"USER_Total_TruckMinutes":null,"USER_Total_TruckTravelTime":null,"USER_Total_WalkTime":null,"USER_Total_Kilometers":0.53262140678947401,"USER_Total_Miles":null,"USER_Shape_Length":0.0064865741250466581}}]
}