{
  "type" : "FeatureCollection",
  "features" : [{"type":"Feature","id":1,"geometry":{"type":"Point","coordinates":[16.384744251000029,48.198402593000026]},"properties":{"ObjectID":1,"Loc_name":"World","Status":"M","Score":97.840000000000003,"Match_type":"A","Match_addr":"Strohgasse 12, 1030, Landstraße, Wien, Wien(Stadt), Wien","LongLabel":"Strohgasse 12, 1030, Landstraße, Wien, Wien(Stadt), Wien, AUT","ShortLabel":"Strohgasse 12","Addr_type":"PointAddress","Type":"","PlaceName":"","Place_addr":"Strohgasse 12, 1030, Landstraße, Wien, Wien(Stadt), Wien","Phone":"","URL":"","Rank":20,"AddBldg":"","AddNum":"12","AddNumFrom":"","AddNumTo":"","AddRange":"","Side":"","StPreDir":"","StPreType":"","StName":"Strohgasse","StType":"","StDir":"","BldgType":"","BldgName":"","LevelType":"","LevelName":"","UnitType":"","UnitName":"","SubAddr":"","StAddr":"Strohgasse 12","Block":"","Sector":"","Nbrhd":"","District":"Landstraße","City":"Wien","MetroArea":"","Subregion":"Wien(Stadt)","Region":"Wien","RegionAbbr":"","Territory":"","Zone":"","Postal":"1030","PostalExt":"","Country":"AUT","CntryName":"Österreich","LangCode":"GER","Distance":0,"X":16.384746346802,"Y":48.198366047907001,"DisplayX":16.384744251326001,"DisplayY":48.198402593005,"Xmin":16.383744251326,"Xmax":16.385744251325999,"Ymin":48.197402593005002,"Ymax":48.199402593004997,"ExInfo":"1030 | WIEN | WIEN","StrucType":"","StrucDet":"","IN_Address":"Strohgasse 12, 1030, Landstraße, Wien, Wien(Stadt), Wien","IN_Address2":null,"IN_Address3":null,"IN_Neighborhood":null,"IN_City":"Wien","IN_Subregion":null,"IN_Region":null,"IN_Postal":"1030","IN_PostalExt":null,"IN_CountryCode":null,"USER_ObjectID":103,"USER_FacilityID":110,"USER_FacilityRank":1,"USER_Address":"Strohgasse 12, 1030, Landstraße, Wien, Wien(Stadt), Wien","USER_City":"Wien","USER_Postal":1030,"USER_Cluster":"Location 52","USER_IncidentCurbApproach":2,"USER_FacilityCurbApproach":1,"USER_IncidentID":52,"USER_StartTime":null,"USER_EndTime":null,"USER_StartTimeUTC":null,"USER_EndTimeUTC":null,"USER_Total_Minutes":null,"USER_Total_TimeAt1KPH":null,"USER_Total_TravelTime":0.32788231904444232,"USER_Total_TruckMinutes":null,"USER_Total_TruckTravelTime":null,"USER_Total_WalkTime":null,"USER_Total_Kilometers":0.079762617186932505,"USER_Total_Miles":null,"USER_Shape_Length":0.0010714218047035971}},{"type":"Feature","id":2,"geometry":{"type":"Point","coordinates":[16.384990428000037,48.198504559000071]},"properties":{"ObjectID":2,"Loc_name":"World","Status":"M","Score":97.939999999999998,"Match_type":"A","Match_addr":"Rechte Bahngasse 40, 1030, Landstraße, Wien, Wien(Stadt), Wien","LongLabel":"Rechte Bahngasse 40, 1030, Landstraße, Wien, Wien(Stadt), Wien, AUT","ShortLabel":"Rechte Bahngasse 40","Addr_type":"PointAddress","Type":"","PlaceName":"","Place_addr":"Rechte Bahngasse 40, 1030, Landstraße, Wien, Wien(Stadt), Wien","Phone":"","URL":"","Rank":20,"AddBldg":"","AddNum":"40","AddNumFrom":"","AddNumTo":"","AddRange":"","Side":"","StPreDir":"","StPreType":"","StName":"Rechte Bahngasse","StType":"","StDir":"","BldgType":"","BldgName":"","LevelType":"","LevelName":"","UnitType":"","UnitName":"","SubAddr":"","StAddr":"Rechte Bahngasse 40","Block":"","Sector":"","Nbrhd":"","District":"Landstraße","City":"Wien","MetroArea":"","Subregion":"Wien(Stadt)","Region":"Wien","RegionAbbr":"","Territory":"","Zone":"","Postal":"1030","PostalExt":"","Country":"AUT","CntryName":"Österreich","LangCode":"GER","Distance":0,"X":16.385083886042999,"Y":48.198531800041998,"DisplayX":16.384990427822,"DisplayY":48.198504558857003,"Xmin":16.383990427821999,"Xmax":16.385990427822001,"Ymin":48.197504558856998,"Ymax":48.199504558857001,"ExInfo":"1030 | WIEN | WIEN","StrucType":"","StrucDet":"","IN_Address":"Rechte Bahngasse 40, 1030, Landstraße, Wien, Wien(Stadt), Wien","IN_Address2":null,"IN_Address3":null,"IN_Neighborhood":null,"IN_City":"Wien","IN_Subregion":null,"IN_Region":null,"IN_Postal":"1030","IN_PostalExt":null,"IN_CountryCode":null,"USER_ObjectID":104,"USER_FacilityID":112,"USER_FacilityRank":2,"USER_Address":"Rechte Bahngasse 40, 1030, Landstraße, Wien, Wien(Stadt), Wien","USER_City":"Wien","USER_Postal":1030,"USER_Cluster":"Location 52","USER_IncidentCurbApproach":2,"USER_FacilityCurbApproach":1,"USER_IncidentID":52,"USER_StartTime":null,"USER_EndTime":null,"USER_StartTimeUTC":null,"USER_EndTimeUTC":null,"USER_Total_Minutes":null,"USER_Total_TimeAt1KPH":null,"USER_Total_TravelTime":0.69862669463135074,"USER_Total_TruckMinutes":null,"USER_Total_TruckTravelTime":null,"USER_Total_WalkTime":null,"USER_Total_Kilometers":0.13022466866390811,"USER_Total_Miles":null,"USER_Shape_Length":0.001663505291608573}}]
}