{
  "type" : "FeatureCollection",
  "features" : [{"type":"Feature","id":1,"geometry":{"type":"Point","coordinates":[16.401792456000067,48.201702674000046]},"properties":{"ObjectID":1,"Loc_name":"World","Status":"M","Score":97.900000000000006,"Match_type":"A","Match_addr":"Haidingergasse 2, 1030, Landstraße, Wien, Wien(Stadt), Wien","LongLabel":"Haidingergasse 2, 1030, Landstraße, Wien, Wien(Stadt), Wien, AUT","ShortLabel":"Haidingergasse 2","Addr_type":"PointAddress","Type":"","PlaceName":"","Place_addr":"Haidingergasse 2, 1030, Landstraße, Wien, Wien(Stadt), Wien","Phone":"","URL":"","Rank":20,"AddBldg":"","AddNum":"2","AddNumFrom":"","AddNumTo":"","AddRange":"","Side":"","StPreDir":"","StPreType":"","StName":"Haidingergasse","StType":"","StDir":"","BldgType":"","BldgName":"","LevelType":"","LevelName":"","UnitType":"","UnitName":"","SubAddr":"","StAddr":"Haidingergasse 2","Block":"","Sector":"","Nbrhd":"","District":"Landstraße","City":"Wien","MetroArea":"","Subregion":"Wien(Stadt)","Region":"Wien","RegionAbbr":"","Territory":"","Zone":"","Postal":"1030","PostalExt":"","Country":"AUT","CntryName":"Österreich","LangCode":"GER","Distance":0,"X":16.401936959661999,"Y":48.201584070084003,"DisplayX":16.401792455652,"DisplayY":48.201702674012999,"Xmin":16.400792455651999,"Xmax":16.402792455652001,"Ymin":48.200702674013002,"Ymax":48.202702674012997,"ExInfo":"1030 | WIEN | WIEN","StrucType":"","StrucDet":"","IN_Address":"Haidingergasse 2, 1030, Landstraße, Wien, Wien(Stadt), Wien","IN_Address2":null,"IN_Address3":null,"IN_Neighborhood":null,"IN_City":"Wien","IN_Subregion":null,"IN_Region":null,"IN_Postal":"1030","IN_PostalExt":null,"IN_CountryCode":null,"USER_ObjectID":48,"USER_FacilityID":310,"USER_FacilityRank":2,"USER_Address":"Haidingergasse 2, 1030, Landstraße, Wien, Wien(Stadt), Wien","USER_City":"Wien","USER_Postal":1030,"USER_Cluster":"Location 24","USER_IncidentCurbApproach":1,"USER_FacilityCurbApproach":1,"USER_IncidentID":24,"USER_StartTime":null,"USER_EndTime":null,"USER_StartTimeUTC":null,"USER_EndTimeUTC":null,"USER_Total_Minutes":null,"USER_Total_TimeAt1KPH":null,"USER_Total_TravelTime":1.4154351720594129,"USER_Total_TruckMinutes":null,"USER_Total_TruckTravelTime":null,"USER_Total_WalkTime":null,"USER_Total_Kilometers":0.44257996650426229,"USER_Total_Miles":null,"USER_Shape_Length":0.0046871005256242868}},{"type":"Feature","id":2,"geometry":{"type":"Point","coordinates":[16.403151581000031,48.197266049000064]},"properties":{"ObjectID":2,"Loc_name":"World","Status":"M","Score":97.920000000000002,"Match_type":"A","Match_addr":"Erdbergstraße 85, 1030, Landstraße, Wien, Wien(Stadt), Wien","LongLabel":"Erdbergstraße 85, 1030, Landstraße, Wien, Wien(Stadt), Wien, AUT","ShortLabel":"Erdbergstraße 85","Addr_type":"PointAddress","Type":"","PlaceName":"","Place_addr":"Erdbergstraße 85, 1030, Landstraße, Wien, Wien(Stadt), Wien","Phone":"","URL":"","Rank":20,"AddBldg":"","AddNum":"85","AddNumFrom":"","AddNumTo":"","AddRange":"","Side":"","StPreDir":"","StPreType":"","StName":"Erdbergstraße","StType":"","StDir":"","BldgType":"","BldgName":"","LevelType":"","LevelName":"","UnitType":"","UnitName":"","SubAddr":"","StAddr":"Erdbergstraße 85","Block":"","Sector":"","Nbrhd":"","District":"Landstraße","City":"Wien","MetroArea":"","Subregion":"Wien(Stadt)","Region":"Wien","RegionAbbr":"","Territory":"","Zone":"","Postal":"1030","PostalExt":"","Country":"AUT","CntryName":"Österreich","LangCode":"GER","Distance":0,"X":16.403128028104,"Y":48.197206453512003,"DisplayX":16.403151581252001,"DisplayY":48.197266048844,"Xmin":16.402151581251999,"Xmax":16.404151581251998,"Ymin":48.196266048844002,"Ymax":48.198266048843998,"ExInfo":"1030 | WIEN | WIEN","StrucType":"","StrucDet":"","IN_Address":"Erdbergstraße 85, 1030, Landstraße, Wien, Wien(Stadt), Wien","IN_Address2":null,"IN_Address3":null,"IN_Neighborhood":null,"IN_City":"Wien","IN_Subregion":null,"IN_Region":null,"IN_Postal":"1030","IN_PostalExt":null,"IN_CountryCode":null,"USER_ObjectID":47,"USER_FacilityID":353,"USER_FacilityRank":1,"USER_Address":"Erdbergstraße 85, 1030, Landstraße, Wien, Wien(Stadt), Wien","USER_City":"Wien","USER_Postal":1030,"USER_Cluster":"Location 24","USER_IncidentCurbApproach":2,"USER_FacilityCurbApproach":1,"USER_IncidentID":24,"USER_StartTime":null,"USER_EndTime":null,"USER_StartTimeUTC":null,"USER_EndTimeUTC":null,"USER_Total_Minutes":null,"USER_Total_TimeAt1KPH":null,"USER_Total_TravelTime":0.84315098437052116,"USER_Total_TruckMinutes":null,"USER_Total_TruckTravelTime":null,"USER_Total_WalkTime":null,"USER_Total_Kilometers":0.26955193753946283,"USER_Total_Miles":null,"USER_Shape_Length":0.003253101827246209}}]
}